admmsolver/__init__.py
admmsolver/matrix.py
admmsolver/objectivefunc.py
admmsolver/optimizer.py
admmsolver/py.typed
admmsolver/util.py
admmsolver-0.7.7.dist-info/LICENSE.txt
admmsolver-0.7.7.dist-info/METADATA
admmsolver-0.7.7.dist-info/WHEEL
admmsolver-0.7.7.dist-info/top_level.txt
admmsolver-0.7.7.dist-info/RECORD
